trudge/__init__.py
trudge/scratch.py
trudge/trudge.py
trudge-0.0.0.3.dist-info/LICENSE
trudge-0.0.0.3.dist-info/METADATA
trudge-0.0.0.3.dist-info/WHEEL
trudge-0.0.0.3.dist-info/top_level.txt
trudge-0.0.0.3.dist-info/RECORD
