Metadata-Version: 2.1
Name: trudge
Version: 0.0.0.3
Summary: Generators that enumerate discrete spaces using various strategies.
Home-page: https://github.com/reity/trudge
Author: Andrei Lapets
Author-email: a@lapets.io
License: MIT
Platform: UNKNOWN
